cfddns/__init__.py
cfddns/__main__.py
cfddns/cfapi.py
cfddns/cli.py
cfddns/dns.py
cfddns/iptools.py
simple_cfddns-2.0.0.dist-info/LICENSE
simple_cfddns-2.0.0.dist-info/METADATA
simple_cfddns-2.0.0.dist-info/WHEEL
simple_cfddns-2.0.0.dist-info/entry_points.txt
simple_cfddns-2.0.0.dist-info/top_level.txt
simple_cfddns-2.0.0.dist-info/RECORD
