Metadata-Version: 2.1
Name: simple-cfddns
Version: 2.0.0
Summary: A simple Cloudflare DDNS service
Author-email: JCav <micojcav@outlook.com>
Project-URL: Homepage, https://github.com/GJCav/cfddns
Project-URL: Bug Tracker, https://github.com/GJCav/cfddns/issues
Classifier: Programming Language :: Python :: 3
Classifier: License :: OSI Approved :: GNU General Public License v3 (GPLv3)
Classifier: Operating System :: OS Independent
Classifier: Topic :: System :: Networking
Classifier: Topic :: Internet :: Name Service (DNS)
Requires-Python: >=3.7
License-File: LICENSE
Requires-Dist: requests
Requires-Dist: psutil
